dstf/__init__.py
dstf/constraints.py
dstf/core.py
dstf/operators.py
dstf/properties.py
tests/__init__.py
tests/test_constraints.py
tests/test_core.py
tests/test_operators.py
tests/test_properties.py
dstf-0.0.12.dist-info/LICENSE
dstf-0.0.12.dist-info/METADATA
dstf-0.0.12.dist-info/WHEEL
dstf-0.0.12.dist-info/top_level.txt
dstf-0.0.12.dist-info/RECORD
