Metadata-Version: 2.1
Name: dstf
Version: 0.0.12
Summary: A framework for Deterministic Scheduling Theory
Home-page: https://github.com/anthonydugois/dstf
Author: Anthony Dugois
Author-email: hello@anthonydugois.com
License: UNKNOWN
Keywords: deterministic scheduling theory
Platform: UNKNOWN
Classifier: License :: OSI Approved :: MIT License
Classifier: Operating System :: OS Independent
Classifier: Programming Language :: Python :: 3
Classifier: Topic :: Scientific/Engineering
